putkoffs_mod/__init__.py
putkoffs_mod-0.1.0.dist-info/METADATA
putkoffs_mod-0.1.0.dist-info/WHEEL
putkoffs_mod-0.1.0.dist-info/top_level.txt
putkoffs_mod-0.1.0.dist-info/RECORD
