Metadata-Version: 2.1
Name: putkoffs-mod
Version: 0.1.0
Summary: putkoffs stuff
Home-page: https://github.com/your_username/putkoffs_mod
Author: putkoff
Author-email: putkey2@sbcglobal.net
License: UNKNOWN
Platform: UNKNOWN
Classifier: Development Status :: 3 - Alpha
Classifier: Intended Audience :: Developers
Classifier: License :: OSI Approved :: MIT License
Classifier: Programming Language :: Python :: 3
Classifier: Programming Language :: Python :: 3.6
Classifier: Programming Language :: Python :: 3.7
Classifier: Programming Language :: Python :: 3.8
Classifier: Programming Language :: Python :: 3.9
